{
    "configurations": [
        {
            "name": "MinGW",
            "intelliSenseMode": "linux-gcc-x64",
            "compilerPath": "/usr/bin/g++",
            "includePath": [
                "${workspaceFolder}",
                "/usr/include/c++/13/"
            ],
            "defines": [],
            "browse": {
                "path": [
                    "${workspaceFolder}",
                    "/usr/include/c++/13/"
                ],
                "limitSymbolsToIncludedHeaders": true,
                "databaseFilename": ""
            },
            "cStandard": "c11",
            "cppStandard": "c++11"
        }
    ],
    "version": 4
}